mycalc/calculator.py
chaehwan-0.0.1.dist-info/LICENSE
chaehwan-0.0.1.dist-info/METADATA
chaehwan-0.0.1.dist-info/WHEEL
chaehwan-0.0.1.dist-info/top_level.txt
chaehwan-0.0.1.dist-info/RECORD
