Metadata-Version: 2.1
Name: chaehwan
Version: 0.0.1
Summary: nice calculator
Home-page: https://github.com/JeonChaeHwan/calc0001
Download-URL: https://github.com/JeonChaeHwan/calc0001/
Author: jchwan
Classifier: Programming Language :: Python :: 3
License-File: LICENSE
